setup.py
neat_py/__init__.py
neat_py/agent.py
neat_py/connection.py
neat_py/genome.py
neat_py/main.py
neat_py/neat_settings.py
neat_py/node.py
neat_py/population.py
neat_py/species.py
neat_py_lollo-0.0.5.dist-info/METADATA
neat_py_lollo-0.0.5.dist-info/WHEEL
neat_py_lollo-0.0.5.dist-info/licenses/LICENSE
neat_py_lollo-0.0.5.dist-info/RECORD
