Metadata-Version: 2.1
Name: neat_py_lollo
Version: 0.0.5
Summary: A python implementation of NEAT
Project-URL: Homepage, https://github.com/15lollo15/NEAT_PY
Project-URL: Bug Tracker, https://github.com/15lollo15/NEAT_PY/issues
Author-email: Racca Lorenzo <lorenzo_racca@hotmail.com>
License-File: LICENSE
Classifier: License :: OSI Approved :: MIT License
Classifier: Operating System :: OS Independent
Classifier: Programming Language :: Python :: 3
Requires-Python: >=3.7
